README.rst
setup.cfg
setup.py
apysignature/__init__.py
apysignature/query_encoder.py
apysignature/signature.py
apysignature.egg-info/PKG-INFO
apysignature.egg-info/SOURCES.txt
apysignature.egg-info/dependency_links.txt
apysignature.egg-info/top_level.txt