Metadata-Version: 1.1
Name: apysignature
Version: 0.2.1
Summary: Python implementation of the Ruby Signature library (https://github.com/mloughran/signature)
Home-page: https://github.com/erickponce/apysignature
Author: Erick Ponce Leão
Author-email: erickponceleao@gmail.com
License: Apache 2.0
Platform: UNKNOWN
Classifier: Environment :: Web Environment
Classifier: Intended Audience :: Developers
Classifier: License :: OSI Approved :: Apache Software License
Classifier: Operating System :: OS Independent
Classifier: Programming Language :: Python
Classifier: Programming Language :: Python :: 2
Classifier: Programming Language :: Python :: 3
Classifier: Topic :: Software Development :: Libraries
